markdown_writer/__init__.py
markdown_writer/core.py
python_markdown_writer-0.2.1.dist-info/METADATA
python_markdown_writer-0.2.1.dist-info/WHEEL
python_markdown_writer-0.2.1.dist-info/top_level.txt
python_markdown_writer-0.2.1.dist-info/RECORD
