Metadata-Version: 2.4
Name: python-markdown-writer
Version: 0.2.1
Summary: Create Markdown documents from within your Python code.
Requires-Python: >=3.8
Requires-Dist: pandas>=2.0.3
Requires-Dist: tabulate>=0.9.0
